src/main.py
src/helper/__init__.py
src/helper/add_passwd_db.py
src/helper/mypasswd_helper.py
src/helper/rsa_crypt.py
mypasswd_rsa-1.0.0.dist-info/METADATA
mypasswd_rsa-1.0.0.dist-info/WHEEL
mypasswd_rsa-1.0.0.dist-info/entry_points.txt
mypasswd_rsa-1.0.0.dist-info/top_level.txt
mypasswd_rsa-1.0.0.dist-info/RECORD
