Metadata-Version: 2.4
Name: mypasswd-rsa
Version: 1.0.0
Summary: A local password app
Requires-Python: >=3.12
Requires-Dist: rich
Requires-Dist: rsa
